parquet_viewer/__init__.py
parquet_viewer/cli.py
parquet_viewer/viewer.py
parquet_viewer-0.1.3.dist-info/LICENSE
parquet_viewer-0.1.3.dist-info/METADATA
parquet_viewer-0.1.3.dist-info/WHEEL
parquet_viewer-0.1.3.dist-info/entry_points.txt
parquet_viewer-0.1.3.dist-info/top_level.txt
parquet_viewer-0.1.3.dist-info/RECORD
