Metadata-Version: 2.1
Name: parquet-viewer
Version: 0.1.3
Summary: A powerful command-line tool for viewing Parquet files
Home-page: https://github.com/Ashlo/ParquetViewer
Author: Ashutosh Bele
Author-email: ashutoshbele5@gmail.com
Classifier: Programming Language :: Python :: 3
Classifier: License :: OSI Approved :: MIT License
Classifier: Operating System :: OS Independent
Requires-Python: >=3.6
License-File: LICENSE
Requires-Dist: pandas
Requires-Dist: pyarrow
Requires-Dist: tabulate
Requires-Dist: click
